nonebot_plugin_what2eat/__init__.py
nonebot_plugin_what2eat/config.py
nonebot_plugin_what2eat/data_source.py
nonebot_plugin_what2eat/resource/drinks.json
nonebot_plugin_what2eat/resource/eating.json
nonebot_plugin_what2eat/resource/greetings.json
nonebot_plugin_what2eat/utils.py
nonebot_plugin_what2eat-0.3.6.dist-info/LICENSE
nonebot_plugin_what2eat-0.3.6.dist-info/METADATA
nonebot_plugin_what2eat-0.3.6.dist-info/WHEEL
nonebot_plugin_what2eat-0.3.6.dist-info/RECORD
