Metadata-Version: 2.1
Name: nonebot-plugin-what2eat
Version: 0.3.6
Summary: Ask bot for what to eat or what to drink!
Home-page: https://github.com/MinatoAquaCrews/nonebot_plugin_what2eat
License: MIT
Keywords: nonebot2,nonebot-plugin,What2eat,What2drink,MinatoAquaCrews
Author: KafCoppelia
Author-email: k740677208@gmail.com
Requires-Python: >=3.8,<4.0
Classifier: License :: OSI Approved :: MIT License
Classifier: Programming Language :: Python :: 3
Classifier: Programming Language :: Python :: 3.8
Classifier: Programming Language :: Python :: 3.9
Classifier: Programming Language :: Python :: 3.10
Classifier: Programming Language :: Python :: 3.11
Requires-Dist: aiofiles (>=0.8.0,<0.9.0)
Requires-Dist: httpx (>=0.23.0,<0.24.0)
Requires-Dist: nonebot-adapter-onebot (>=2.1.3,<3.0.0)
Requires-Dist: nonebot-plugin-apscheduler (>=0.2.0,<0.3.0)
Requires-Dist: nonebot2 (>=2.0.0rc1,<3.0.0)
Project-URL: Documentation, https://github.com/MinatoAquaCrews/nonebot_plugin_what2eat#readme
Project-URL: Repository, https://github.com/MinatoAquaCrews/nonebot_plugin_what2eat
